{"updated":"2026-06-04 21:19 (VN)","data_time":"2026-06-04 14:45","vn30f":1982.4,"session_date":"2026-06-04","go_live":"2026-06-01","contracts":2,"mult":100000,"start_capital":100000000,"cost_rt_vnd":50000,"totals":{"today_w":6,"today_l":7,"today_gpts":0.2,"today_gross":38446,"today_fee":1300000,"today_net":-1261554,"fwd_w":23,"fwd_l":31,"fwd_gpts":36.2,"fwd_gross":7238145,"fwd_fee":5400000,"fwd_net":1838145,"cap_total":1500000000,"equity_total":1501838145,"ret_pct":0.12},"opens":[{"name":"BÒ RỪNG","icon":"🦬","tf":"1h","side":"long","entry":1971.3,"vao":"10:00","unreal":11.1,"unreal_vnd":2220000,"hd":2},{"name":"CÁ MẬP","icon":"🦈","tf":"5m","side":"long","entry":1980.9,"vao":"14:05","unreal":1.5,"unreal_vnd":300000,"hd":2},{"name":"BÁO ĐEN","icon":"🐈‍⬛","tf":"30m","side":"long","entry":1973.0,"vao":"09:30","unreal":9.4,"unreal_vnd":1880000,"hd":2},{"name":"BÁO ĐỐM","icon":"🐯","tf":"30m","side":"long","entry":1976.1,"vao":"13:30","unreal":6.3,"unreal_vnd":1260000,"hd":2},{"name":"HỔ","icon":"🐅","tf":"5m","side":"long","entry":1980.2,"vao":"14:15","unreal":2.2,"unreal_vnd":440000,"hd":2}],"packs":[{"name":"Đa dạng 5 trụ","members":["BÁO SĂN","ĐẠI BÀNG","GẤU","HỔ MANG","CÁ MẬP"],"n":5,"cap":500000000,"today_net":2800000,"fwd_net":7434560,"fwd_gross":8734560,"fwd_fee":1300000,"fwd_w":7,"fwd_l":6,"fwd_n":13,"wr":54,"n_open":1,"equity":507434560,"ret_pct":1.49},{"name":"Lục trụ","members":["BÁO SĂN","ĐẠI BÀNG","BÁO ĐEN","GẤU","HỔ MANG","CÁ MẬP"],"n":6,"cap":600000000,"today_net":2580000,"fwd_net":7168287,"fwd_gross":9068287,"fwd_fee":1900000,"fwd_w":9,"fwd_l":10,"fwd_n":19,"wr":47,"n_open":2,"equity":607168287,"ret_pct":1.19}],"strats":[{"name":"LINH MIÊU","icon":"🐈","tf":"15m","ok":true,"today_w":1,"today_l":0,"today_gpts":14.9,"today_gross":2980000,"today_fee":100000,"today_net":2880000,"fwd_w":2,"fwd_l":3,"fwd_n":5,"fwd_gpts":-9.7,"fwd_gross":-1931548,"fwd_fee":500000,"fwd_net":-2431548,"open":null,"equity":97568452,"ret_pct":-2.43,"trades":[{"side":"short","vao":"03 13:30","ra":"09:00","epx":1985.5,"xpx":1970.6,"pts":14.4,"ly":"signal"}]},{"name":"ĐẠI BÀNG","icon":"🦅","tf":"30m","ok":true,"today_w":1,"today_l":0,"today_gpts":12.5,"today_gross":2500000,"today_fee":100000,"today_net":2400000,"fwd_w":2,"fwd_l":2,"fwd_n":4,"fwd_gpts":-4.7,"fwd_gross":-945431,"fwd_fee":400000,"fwd_net":-1345431,"open":null,"equity":98654569,"ret_pct":-1.35,"trades":[{"side":"short","vao":"03 13:30","ra":"09:00","epx":1985.5,"xpx":1973.0,"pts":12.0,"ly":"signal"}]},{"name":"BÁO SĂN","icon":"🐆","tf":"5m","ok":true,"today_w":1,"today_l":0,"today_gpts":2.5,"today_gross":500000,"today_fee":100000,"today_net":400000,"fwd_w":3,"fwd_l":3,"fwd_n":6,"fwd_gpts":10.3,"fwd_gross":2066467,"fwd_fee":600000,"fwd_net":1466467,"open":null,"equity":101466467,"ret_pct":1.47,"trades":[{"side":"short","vao":"03 14:45","ra":"09:00","epx":1972.4,"xpx":1969.9,"pts":2.0,"ly":"signal"}]},{"name":"CHIM CẮT","icon":"🐦‍⬛","tf":"5m","ok":true,"today_w":1,"today_l":0,"today_gpts":2.5,"today_gross":500000,"today_fee":100000,"today_net":400000,"fwd_w":2,"fwd_l":3,"fwd_n":5,"fwd_gpts":3.4,"fwd_gross":680000,"fwd_fee":500000,"fwd_net":180000,"open":null,"equity":100180000,"ret_pct":0.18,"trades":[{"side":"short","vao":"03 14:45","ra":"09:00","epx":1972.4,"xpx":1969.9,"pts":2.0,"ly":"signal"}]},{"name":"DIỀU HÂU","icon":"🦉","tf":"5m","ok":true,"today_w":1,"today_l":0,"today_gpts":2.5,"today_gross":500000,"today_fee":100000,"today_net":400000,"fwd_w":3,"fwd_l":3,"fwd_n":6,"fwd_gpts":10.3,"fwd_gross":2066467,"fwd_fee":600000,"fwd_net":1466467,"open":null,"equity":101466467,"ret_pct":1.47,"trades":[{"side":"short","vao":"03 14:45","ra":"09:00","epx":1972.4,"xpx":1969.9,"pts":2.0,"ly":"signal"}]},{"name":"GẤU","icon":"🐻","tf":"1h","ok":true,"today_w":0,"today_l":0,"today_gpts":0.0,"today_gross":0,"today_fee":0,"today_net":0,"fwd_w":0,"fwd_l":0,"fwd_n":0,"fwd_gpts":0.0,"fwd_gross":0,"fwd_fee":0,"fwd_net":0,"open":null,"equity":100000000,"ret_pct":0.0,"trades":[]},{"name":"TÊ GIÁC","icon":"🦏","tf":"1h","ok":true,"today_w":0,"today_l":0,"today_gpts":0.0,"today_gross":0,"today_fee":0,"today_net":0,"fwd_w":0,"fwd_l":0,"fwd_n":0,"fwd_gpts":0.0,"fwd_gross":0,"fwd_fee":0,"fwd_net":0,"open":null,"equity":100000000,"ret_pct":0.0,"trades":[]},{"name":"BÒ RỪNG","icon":"🦬","tf":"1h","ok":true,"today_w":0,"today_l":0,"today_gpts":0.0,"today_gross":0,"today_fee":0,"today_net":0,"fwd_w":0,"fwd_l":0,"fwd_n":0,"fwd_gpts":0.0,"fwd_gross":0,"fwd_fee":0,"fwd_net":0,"open":{"name":"BÒ RỪNG","icon":"🦬","tf":"1h","side":"long","entry":1971.3,"vao":"10:00","unreal":11.1,"unreal_vnd":2220000,"hd":2},"equity":100000000,"ret_pct":0.0,"trades":[]},{"name":"HỔ MANG","icon":"🐍","tf":"30m","ok":true,"today_w":0,"today_l":0,"today_gpts":0.0,"today_gross":0,"today_fee":0,"today_net":0,"fwd_w":1,"fwd_l":0,"fwd_n":1,"fwd_gpts":37.3,"fwd_gross":7460927,"fwd_fee":100000,"fwd_net":7360927,"open":null,"equity":107360927,"ret_pct":7.36,"trades":[]},{"name":"SƯ TỬ","icon":"🦁","tf":"1h","ok":true,"today_w":0,"today_l":0,"today_gpts":0.0,"today_gross":0,"today_fee":0,"today_net":0,"fwd_w":0,"fwd_l":0,"fwd_n":0,"fwd_gpts":0.0,"fwd_gross":0,"fwd_fee":0,"fwd_net":0,"open":null,"equity":100000000,"ret_pct":0.0,"trades":[]},{"name":"CHÓ SÓI","icon":"🐺","tf":"1h","ok":true,"today_w":0,"today_l":0,"today_gpts":0.0,"today_gross":0,"today_fee":0,"today_net":0,"fwd_w":0,"fwd_l":0,"fwd_n":0,"fwd_gpts":0.0,"fwd_gross":0,"fwd_fee":0,"fwd_net":0,"open":null,"equity":100000000,"ret_pct":0.0,"trades":[]},{"name":"CÁ MẬP","icon":"🦈","tf":"5m","ok":true,"today_w":0,"today_l":0,"today_gpts":0.0,"today_gross":0,"today_fee":0,"today_net":0,"fwd_w":1,"fwd_l":1,"fwd_n":2,"fwd_gpts":0.8,"fwd_gross":152597,"fwd_fee":200000,"fwd_net":-47403,"open":{"name":"CÁ MẬP","icon":"🦈","tf":"5m","side":"long","entry":1980.9,"vao":"14:05","unreal":1.5,"unreal_vnd":300000,"hd":2},"equity":99952597,"ret_pct":-0.05,"trades":[]},{"name":"BÁO ĐEN","icon":"🐈‍⬛","tf":"30m","ok":true,"today_w":0,"today_l":1,"today_gpts":-0.6,"today_gross":-120000,"today_fee":100000,"today_net":-220000,"fwd_w":2,"fwd_l":4,"fwd_n":6,"fwd_gpts":1.7,"fwd_gross":333727,"fwd_fee":600000,"fwd_net":-266273,"open":{"name":"BÁO ĐEN","icon":"🐈‍⬛","tf":"30m","side":"long","entry":1973.0,"vao":"09:30","unreal":9.4,"unreal_vnd":1880000,"hd":2},"equity":99733727,"ret_pct":-0.27,"trades":[{"side":"short","vao":"03 14:30","ra":"09:00","epx":1972.4,"xpx":1973.0,"pts":-1.1,"ly":"signal"}]},{"name":"BÁO ĐỐM","icon":"🐯","tf":"30m","ok":true,"today_w":0,"today_l":2,"today_gpts":-11.5,"today_gross":-2293276,"today_fee":200000,"today_net":-2493276,"fwd_w":2,"fwd_l":4,"fwd_n":6,"fwd_gpts":-3.1,"fwd_gross":-611941,"fwd_fee":600000,"fwd_net":-1211941,"open":{"name":"BÁO ĐỐM","icon":"🐯","tf":"30m","side":"long","entry":1976.1,"vao":"13:30","unreal":6.3,"unreal_vnd":1260000,"hd":2},"equity":98788059,"ret_pct":-1.21,"trades":[{"side":"short","vao":"03 14:30","ra":"09:00","epx":1972.4,"xpx":1973.0,"pts":-1.1,"ly":"signal"},{"side":"short","vao":"10:30","ra":"13:00","epx":1969.6,"xpx":1980.5,"pts":-11.37,"ly":"stop"}]},{"name":"HỔ","icon":"🐅","tf":"5m","ok":true,"today_w":1,"today_l":4,"today_gpts":-22.6,"today_gross":-4528278,"today_fee":500000,"today_net":-5028278,"fwd_w":5,"fwd_l":8,"fwd_n":13,"fwd_gpts":-10.2,"fwd_gross":-2033120,"fwd_fee":1300000,"fwd_net":-3333120,"open":{"name":"HỔ","icon":"🐅","tf":"5m","side":"long","entry":1980.2,"vao":"14:15","unreal":2.2,"unreal_vnd":440000,"hd":2},"equity":96666880,"ret_pct":-3.33,"trades":[{"side":"short","vao":"03 14:45","ra":"09:00","epx":1972.4,"xpx":1969.9,"pts":2.0,"ly":"signal"},{"side":"short","vao":"09:20","ra":"13:10","epx":1968.0,"xpx":1980.1,"pts":-12.6,"ly":"stop"},{"side":"long","vao":"13:10","ra":"13:20","epx":1978.6,"xpx":1976.2,"pts":-2.9,"ly":"stop"},{"side":"short","vao":"13:45","ra":"14:00","epx":1979.7,"xpx":1982.3,"pts":-3.14,"ly":"stop"},{"side":"short","vao":"14:10","ra":"14:15","epx":1977.6,"xpx":1985.6,"pts":-8.51,"ly":"stop"}]}],"forward":{"ok":true,"go_live":"2026-06-04","animals":[{"name":"SÓI LỬA","tf":"15m","ok":true,"today_w":0,"today_l":0,"today_gpts":0.0,"today_gross":0,"today_fee":0,"today_net":0,"fwd_w":0,"fwd_l":0,"fwd_n":0,"fwd_gpts":0.0,"fwd_gross":0,"fwd_fee":0,"fwd_net":0,"open":null,"equity":100000000,"ret_pct":0.0},{"name":"CÁ SẤU","tf":"5m","ok":true,"today_w":0,"today_l":1,"today_gpts":-4.1,"today_gross":-820000,"today_fee":100000,"today_net":-920000,"fwd_w":0,"fwd_l":1,"fwd_n":1,"fwd_gpts":-4.1,"fwd_gross":-819477,"fwd_fee":100000,"fwd_net":-919477,"open":null,"equity":99080523,"ret_pct":-0.92},{"name":"LINH CẨU","tf":"5m","ok":true,"today_w":0,"today_l":3,"today_gpts":-9.3,"today_gross":-1866000,"today_fee":300000,"today_net":-2166000,"fwd_w":0,"fwd_l":3,"fwd_n":3,"fwd_gpts":-9.3,"fwd_gross":-1867093,"fwd_fee":300000,"fwd_net":-2167093,"open":{"side":"long","entry":1971.8,"unreal":10.6},"equity":97832907,"ret_pct":-2.17}],"packs":[{"name":"Song tru","members":["SÓI LỬA","CÁ SẤU"],"n":2,"cap":200000000,"today_net":-920000,"fwd_net":-919477,"fwd_gross":-819477,"fwd_fee":100000,"fwd_w":0,"fwd_l":1,"fwd_n":1,"wr":0,"n_open":0,"equity":199080523,"ret_pct":-0.46},{"name":"Tam tru","members":["SÓI LỬA","CÁ SẤU","LINH CẨU"],"n":3,"cap":300000000,"today_net":-3086000,"fwd_net":-3086570,"fwd_gross":-2686570,"fwd_fee":400000,"fwd_w":0,"fwd_l":4,"fwd_n":4,"wr":0,"n_open":1,"equity":296913430,"ret_pct":-1.03}]}}